rnsh/__init__.py
rnsh/args.py
rnsh/docopt.py
rnsh/exception.py
rnsh/helpers.py
rnsh/initiator.py
rnsh/listener.py
rnsh/loop.py
rnsh/process.py
rnsh/protocol.py
rnsh/retry.py
rnsh/rnsh.py
rnsh/rnslogging.py
rnsh/session.py
rnsh/testlogging.py
rnsh-0.1.7.dist-info/METADATA
rnsh-0.1.7.dist-info/WHEEL
rnsh-0.1.7.dist-info/entry_points.txt
rnsh-0.1.7.dist-info/licenses/LICENSE
rnsh-0.1.7.dist-info/RECORD
